[
    {
        "additions": 3,
        "author": "rajendra-dendukuri",
        "baseRefName": "master",
        "mergedAt": "2020-12-17T14:49:10Z",
        "number": 24,
        "title": "Include port default fec configuration to be included in ZTP config",
        "repo": "sonic-ztp"
    },
    {
        "additions": 161,
        "author": "rajendra-dendukuri",
        "baseRefName": "master",
        "mergedAt": "2020-12-17T14:48:29Z",
        "number": 23,
        "title": "Add a pre-defined plugin to download a list of files",
        "repo": "sonic-ztp"
    },
    {
        "additions": 28,
        "author": "jleveque",
        "baseRefName": "master",
        "mergedAt": "2020-09-19T07:31:54Z",
        "number": 19,
        "title": "Update paths to reflect new sonic-utilities install location, /usr/local/bin/",
        "repo": "sonic-ztp"
    },
    {
        "additions": 12,
        "author": "jleveque",
        "baseRefName": "master",
        "mergedAt": "2020-08-07T00:42:02Z",
        "number": 18,
        "title": "Update all references to new 'sonic-installer' file name",
        "repo": "sonic-ztp"
    },
    {
        "additions": 28,
        "author": "rajendra-dendukuri",
        "baseRefName": "master",
        "mergedAt": "2020-06-25T11:27:07Z",
        "number": 17,
        "title": "Filter out non-printable characters read from syseeprom",
        "repo": "sonic-ztp"
    },
    {
        "additions": 307,
        "author": "rajendra-dendukuri",
        "baseRefName": "master",
        "mergedAt": "2020-09-23T20:21:42Z",
        "number": 16,
        "title": "[MultiDB] Add multidb support to sonic-ztp",
        "repo": "sonic-ztp"
    },
    {
        "additions": 2,
        "author": "rajendra-dendukuri",
        "baseRefName": "master",
        "mergedAt": "2020-04-29T07:10:37Z",
        "number": 14,
        "title": "Fix ztp profile unit test",
        "repo": "sonic-ztp"
    },
    {
        "additions": 64,
        "author": "rajendra-dendukuri",
        "baseRefName": "master",
        "mergedAt": "2020-04-29T07:10:12Z",
        "number": 13,
        "title": "Create a shadow ZTP data json file accessible to non-root user",
        "repo": "sonic-ztp"
    }
]
